<?xml version="1.0" encoding="utf-8" ?><dwsync><file name="campaign.php" server="dev.ensofobi.com//dev/" local="3481389867" remote="318763443874261212" Dst="-1" /><file name="communication.php" server="dev.ensofobi.com//dev/" local="3481392611" remote="318763443874285512" Dst="-1" /><file name="coupons.php" server="dev.ensofobi.com//dev/" local="3481389870" remote="318763443873408012" Dst="-1" /><file name="fobiwords.php" server="dev.ensofobi.com//dev/" local="3481395402" remote="318763443874288272" Dst="-1" /><file name="header.php" server="dev.ensofobi.com//dev/" local="3481389870" remote="318763443870624912" Dst="-1" /><file name="leftaside.php" server="dev.ensofobi.com//dev/" local="3481389871" remote="318763443870617892" Dst="-1" /><file name="keywords.php" server="dev.ensofobi.com//dev/" local="3481389871" remote="318763443872650032" Dst="-1" /><file name="interests.php" server="dev.ensofobi.com//dev/" local="3481391689" remote="318763443874284552" Dst="-1" /><file name="maincontent.php" server="dev.ensofobi.com//dev/" local="3481389872" remote="318763443870619992" Dst="-1" /><file name="merchandise.php" server="dev.ensofobi.com//dev/" local="3481389872" remote="318763443873661212" Dst="-1" /><file name="photo.php" server="dev.ensofobi.com//dev/" local="3481389873" remote="318763443870624072" Dst="-1" /><file name="rightaside.php" server="dev.ensofobi.com//dev/" local="3481389873" remote="318763443870472392" Dst="-1" /><file name="services.php" server="dev.ensofobi.com//dev/" local="3481395178" remote="318763443874288092" Dst="-1" /></dwsync>